consolemenu/__init__.py
consolemenu/console_menu.py
consolemenu/menu_component.py
consolemenu/menu_formatter.py
consolemenu/multiselect_menu.py
consolemenu/prompt_utils.py
consolemenu/screen.py
consolemenu/selection_menu.py
consolemenu/version.py
consolemenu/format/__init__.py
consolemenu/format/menu_borders.py
consolemenu/format/menu_margins.py
consolemenu/format/menu_padding.py
consolemenu/format/menu_style.py
consolemenu/items/__init__.py
consolemenu/items/command_item.py
consolemenu/items/external_item.py
consolemenu/items/function_item.py
consolemenu/items/selection_item.py
consolemenu/items/submenu_item.py
consolemenu/validators/__init__.py
consolemenu/validators/base.py
consolemenu/validators/regex.py
consolemenu/validators/url.py
console_menu-0.8.0.dist-info/LICENSE.md
console_menu-0.8.0.dist-info/METADATA
console_menu-0.8.0.dist-info/WHEEL
console_menu-0.8.0.dist-info/top_level.txt
console_menu-0.8.0.dist-info/RECORD
